sphinx_rtd_theme/__init__.py
sphinx_rtd_theme/breadcrumbs.html
sphinx_rtd_theme/footer.html
sphinx_rtd_theme/layout.html
sphinx_rtd_theme/search.html
sphinx_rtd_theme/searchbox.html
sphinx_rtd_theme/theme.conf
sphinx_rtd_theme/versions.html
sphinx_rtd_theme/locale/sphinx.pot
sphinx_rtd_theme/locale/da/LC_MESSAGES/sphinx.mo
sphinx_rtd_theme/locale/da/LC_MESSAGES/sphinx.po
sphinx_rtd_theme/locale/de/LC_MESSAGES/sphinx.mo
sphinx_rtd_theme/locale/de/LC_MESSAGES/sphinx.po
sphinx_rtd_theme/locale/en/LC_MESSAGES/sphinx.mo
sphinx_rtd_theme/locale/en/LC_MESSAGES/sphinx.po
sphinx_rtd_theme/locale/es/LC_MESSAGES/sphinx.mo
sphinx_rtd_theme/locale/es/LC_MESSAGES/sphinx.po
sphinx_rtd_theme/locale/et/LC_MESSAGES/sphinx.mo
sphinx_rtd_theme/locale/et/LC_MESSAGES/sphinx.po
sphinx_rtd_theme/locale/fa_IR/LC_MESSAGES/sphinx.mo
sphinx_rtd_theme/locale/fa_IR/LC_MESSAGES/sphinx.po
sphinx_rtd_theme/locale/fr/LC_MESSAGES/sphinx.mo
sphinx_rtd_theme/locale/fr/LC_MESSAGES/sphinx.po
sphinx_rtd_theme/locale/hr/LC_MESSAGES/sphinx.mo
sphinx_rtd_theme/locale/hr/LC_MESSAGES/sphinx.po
sphinx_rtd_theme/locale/hu/LC_MESSAGES/sphinx.mo
sphinx_rtd_theme/locale/hu/LC_MESSAGES/sphinx.po
sphinx_rtd_theme/locale/it/LC_MESSAGES/sphinx.mo
sphinx_rtd_theme/locale/it/LC_MESSAGES/sphinx.po
sphinx_rtd_theme/locale/lt/LC_MESSAGES/sphinx.mo
sphinx_rtd_theme/locale/lt/LC_MESSAGES/sphinx.po
sphinx_rtd_theme/locale/nl/LC_MESSAGES/sphinx.mo
sphinx_rtd_theme/locale/nl/LC_MESSAGES/sphinx.po
sphinx_rtd_theme/locale/pl/LC_MESSAGES/sphinx.mo
sphinx_rtd_theme/locale/pl/LC_MESSAGES/sphinx.po
sphinx_rtd_theme/locale/pt/LC_MESSAGES/sphinx.mo
sphinx_rtd_theme/locale/pt/LC_MESSAGES/sphinx.po
sphinx_rtd_theme/locale/pt_BR/LC_MESSAGES/sphinx.mo
sphinx_rtd_theme/locale/pt_BR/LC_MESSAGES/sphinx.po
sphinx_rtd_theme/locale/ru/LC_MESSAGES/sphinx.mo
sphinx_rtd_theme/locale/ru/LC_MESSAGES/sphinx.po
sphinx_rtd_theme/locale/sv/LC_MESSAGES/sphinx.mo
sphinx_rtd_theme/locale/sv/LC_MESSAGES/sphinx.po
sphinx_rtd_theme-3.0.1.dist-info/LICENSE
sphinx_rtd_theme-3.0.1.dist-info/METADATA
sphinx_rtd_theme-3.0.1.dist-info/WHEEL
sphinx_rtd_theme-3.0.1.dist-info/entry_points.txt
sphinx_rtd_theme-3.0.1.dist-info/top_level.txt
sphinx_rtd_theme-3.0.1.dist-info/RECORD
