Metadata-Version: 2.1
Name: sphinx-rtd-theme
Version: 3.0.1
Summary: Read the Docs theme for Sphinx
Home-page: https://github.com/readthedocs/sphinx_rtd_theme
Author: Dave Snider, Read the Docs, Inc. & contributors
Author-email: dev@readthedocs.org
License: MIT
Project-URL: Homepage, https://sphinx-rtd-theme.readthedocs.io/
Project-URL: Source Code, https://github.com/readthedocs/sphinx_rtd_theme
Project-URL: Issue Tracker, https://github.com/readthedocs/sphinx_rtd_theme/issues
Classifier: Framework :: Sphinx
Classifier: Framework :: Sphinx :: Theme
Classifier: Development Status :: 5 - Production/Stable
Classifier: License :: OSI Approved :: MIT License
Classifier: Environment :: Console
Classifier: Environment :: Web Environment
Classifier: Intended Audience :: Developers
Classifier: Programming Language :: Python :: 3
Classifier: Programming Language :: Python :: 3 :: Only
Classifier: Programming Language :: Python :: 3.8
Classifier: Programming Language :: Python :: 3.9
Classifier: Programming Language :: Python :: 3.10
Classifier: Programming Language :: Python :: 3.11
Classifier: Programming Language :: Python :: 3.12
Classifier: Operating System :: OS Independent
Classifier: Topic :: Documentation
Classifier: Topic :: Software Development :: Documentation
Requires-Python: >=3.8
Provides-Extra: dev
License-File: LICENSE
